easyrelease/__init__.py
easyrelease/_nbdev.py
easyrelease/cli.py
easyrelease/conda.py
easyrelease/gh.py
easyrelease/pypi.py
easyrelease/utils.py
easyrelease/templates/__init__.py
easyrelease/templates/bld_template.bat
easyrelease/templates/build_template.sh
easyrelease/templates/gh-release-config-template.yaml
easyrelease/templates/meta_template.yaml
easyrelease/templates/settings_slim_template.ini
easyrelease/templates/settings_template.ini
easyrelease/templates/setup_template.py
easyrelease-0.3.0.dist-info/LICENSE
easyrelease-0.3.0.dist-info/METADATA
easyrelease-0.3.0.dist-info/WHEEL
easyrelease-0.3.0.dist-info/entry_points.txt
easyrelease-0.3.0.dist-info/top_level.txt
easyrelease-0.3.0.dist-info/RECORD
