Metadata-Version: 2.1
Name: easyrelease
Version: 0.3.0
Summary: Tools to automate release to GitHub, pypi and conda
Home-page: https://github.com/PabloRMira/easyrelease/tree/main/
Author: Pablo Rodriguez Mira
Author-email: rodriguez.mira.pablo@gmail.com
License: Apache Software License 2.0
Keywords: github release python pypi conda
Platform: UNKNOWN
Classifier: Development Status :: 4 - Beta
Classifier: Intended Audience :: Developers
Classifier: License :: OSI Approved :: Apache Software License
Classifier: Natural Language :: English
Classifier: Programming Language :: Python :: 3.6
Classifier: Programming Language :: Python :: 3.7
Classifier: Programming Language :: Python :: 3.8
Requires-Python: >=3.6
Requires-Dist: pyyaml (>=5.0.0)
Requires-Dist: requests (>=2.0.0)
Requires-Dist: conda-build (>=3.0.0)
Requires-Dist: anaconda-client (>=1.7.0)
Requires-Dist: twine (>=3.0.0)
